knifes/__init__.py
knifes/aes.py
knifes/alarm.py
knifes/constants.py
knifes/decorators.py
knifes/deploy.py
knifes/digests.py
knifes/envconfig.py
knifes/file.py
knifes/getui.py
knifes/i18n.py
knifes/jsons.py
knifes/logging.py
knifes/luban.py
knifes/media.py
knifes/misc.py
knifes/operators.py
knifes/package.py
knifes/paginator.py
knifes/randoms.py
knifes/results.py
knifes/roar.py
knifes/shell.py
knifes/sms.py
knifes/status.py
knifes/strings.py
knifes/times.py
knifes/urls.py
knifes/useragent.py
knifes/templatetags/__init__.py
knifes/templatetags/locale.py
d_knifes-0.0.2.dist-info/METADATA
d_knifes-0.0.2.dist-info/WHEEL
d_knifes-0.0.2.dist-info/top_level.txt
d_knifes-0.0.2.dist-info/RECORD
